<?xml version="1.0" encoding="UTF-8"?>
<!DOCTYPE dataset SYSTEM "data.dtd">
<!--  Auto-generated by the Maven Impex Plugin -->
<dataset>
    <KREW_RTE_NODE_CFG_PARM_T KEY_CD="contentFragment"
        RTE_NODE_CFG_PARM_ID="2012" RTE_NODE_ID="2004" VAL="&lt;start name=&quot;placeholder&quot;>&lt;activationType>S&lt;/activationType>&lt;/start>"/>
    <KREW_RTE_NODE_CFG_PARM_T KEY_CD="activationType"
        RTE_NODE_CFG_PARM_ID="2013" RTE_NODE_ID="2004" VAL="S"/>
    <KREW_RTE_NODE_CFG_PARM_T KEY_CD="ruleSelector"
        RTE_NODE_CFG_PARM_ID="2014" RTE_NODE_ID="2004" VAL="Template"/>
    <KREW_RTE_NODE_CFG_PARM_T KEY_CD="contentFragment"
        RTE_NODE_CFG_PARM_ID="2015" RTE_NODE_ID="2006" VAL="&lt;start name=&quot;placeholder&quot;>&lt;activationType>S&lt;/activationType>&lt;/start>"/>
    <KREW_RTE_NODE_CFG_PARM_T KEY_CD="activationType"
        RTE_NODE_CFG_PARM_ID="2016" RTE_NODE_ID="2006" VAL="S"/>
    <KREW_RTE_NODE_CFG_PARM_T KEY_CD="ruleSelector"
        RTE_NODE_CFG_PARM_ID="2017" RTE_NODE_ID="2006" VAL="Template"/>
    <KREW_RTE_NODE_CFG_PARM_T KEY_CD="contentFragment"
        RTE_NODE_CFG_PARM_ID="2118" RTE_NODE_ID="2039" VAL="&lt;start name=&quot;Adhoc Routing&quot;>&lt;activationType>S&lt;/activationType>&lt;mandatoryRoute>false&lt;/mandatoryRoute>&lt;finalApproval>true&lt;/finalApproval>&lt;/start>"/>
    <KREW_RTE_NODE_CFG_PARM_T KEY_CD="activationType"
        RTE_NODE_CFG_PARM_ID="2119" RTE_NODE_ID="2039" VAL="S"/>
    <KREW_RTE_NODE_CFG_PARM_T KEY_CD="mandatoryRoute"
        RTE_NODE_CFG_PARM_ID="2120" RTE_NODE_ID="2039" VAL="false"/>
    <KREW_RTE_NODE_CFG_PARM_T KEY_CD="finalApproval"
        RTE_NODE_CFG_PARM_ID="2121" RTE_NODE_ID="2039" VAL="true"/>
    <KREW_RTE_NODE_CFG_PARM_T KEY_CD="ruleSelector"
        RTE_NODE_CFG_PARM_ID="2122" RTE_NODE_ID="2039" VAL="Template"/>
    <KREW_RTE_NODE_CFG_PARM_T KEY_CD="contentFragment"
        RTE_NODE_CFG_PARM_ID="2123" RTE_NODE_ID="2041" VAL="&lt;start name=&quot;Initiated&quot;>&lt;activationType>S&lt;/activationType>&lt;/start>"/>
    <KREW_RTE_NODE_CFG_PARM_T KEY_CD="activationType"
        RTE_NODE_CFG_PARM_ID="2124" RTE_NODE_ID="2041" VAL="S"/>
    <KREW_RTE_NODE_CFG_PARM_T KEY_CD="ruleSelector"
        RTE_NODE_CFG_PARM_ID="2125" RTE_NODE_ID="2041" VAL="Template"/>
    <KREW_RTE_NODE_CFG_PARM_T KEY_CD="contentFragment"
        RTE_NODE_CFG_PARM_ID="2126" RTE_NODE_ID="2042" VAL="&lt;requests name=&quot;ReviewersNode&quot;>&lt;ruleTemplate>ReviewersRouting&lt;/ruleTemplate>&lt;/requests>"/>
    <KREW_RTE_NODE_CFG_PARM_T KEY_CD="ruleTemplate"
        RTE_NODE_CFG_PARM_ID="2127" RTE_NODE_ID="2042" VAL="ReviewersRouting"/>
    <KREW_RTE_NODE_CFG_PARM_T KEY_CD="ruleSelector"
        RTE_NODE_CFG_PARM_ID="2128" RTE_NODE_ID="2042" VAL="Template"/>
    <KREW_RTE_NODE_CFG_PARM_T KEY_CD="contentFragment"
        RTE_NODE_CFG_PARM_ID="2129" RTE_NODE_ID="2043" VAL="&lt;requests name=&quot;RequestsNode&quot;>&lt;ruleTemplate>NotificationRouting&lt;/ruleTemplate>&lt;/requests>"/>
    <KREW_RTE_NODE_CFG_PARM_T KEY_CD="ruleTemplate"
        RTE_NODE_CFG_PARM_ID="2130" RTE_NODE_ID="2043" VAL="NotificationRouting"/>
    <KREW_RTE_NODE_CFG_PARM_T KEY_CD="ruleSelector"
        RTE_NODE_CFG_PARM_ID="2131" RTE_NODE_ID="2043" VAL="Template"/>
    <KREW_RTE_NODE_CFG_PARM_T KEY_CD="contentFragment"
        RTE_NODE_CFG_PARM_ID="2170" RTE_NODE_ID="2061" VAL="&lt;start name=&quot;Initiated&quot;>&lt;activationType>P&lt;/activationType>&lt;mandatoryRoute>false&lt;/mandatoryRoute>&lt;finalApproval>false&lt;/finalApproval>&lt;/start>"/>
    <KREW_RTE_NODE_CFG_PARM_T KEY_CD="activationType"
        RTE_NODE_CFG_PARM_ID="2171" RTE_NODE_ID="2061" VAL="P"/>
    <KREW_RTE_NODE_CFG_PARM_T KEY_CD="mandatoryRoute"
        RTE_NODE_CFG_PARM_ID="2172" RTE_NODE_ID="2061" VAL="false"/>
    <KREW_RTE_NODE_CFG_PARM_T KEY_CD="finalApproval"
        RTE_NODE_CFG_PARM_ID="2173" RTE_NODE_ID="2061" VAL="false"/>
    <KREW_RTE_NODE_CFG_PARM_T KEY_CD="ruleSelector"
        RTE_NODE_CFG_PARM_ID="2174" RTE_NODE_ID="2061" VAL="Template"/>
    <KREW_RTE_NODE_CFG_PARM_T KEY_CD="contentFragment"
        RTE_NODE_CFG_PARM_ID="2175" RTE_NODE_ID="2063" VAL="&lt;start name=&quot;Initiated&quot;>&lt;activationType>P&lt;/activationType>&lt;mandatoryRoute>false&lt;/mandatoryRoute>&lt;finalApproval>false&lt;/finalApproval>&lt;/start>"/>
    <KREW_RTE_NODE_CFG_PARM_T KEY_CD="activationType"
        RTE_NODE_CFG_PARM_ID="2176" RTE_NODE_ID="2063" VAL="P"/>
    <KREW_RTE_NODE_CFG_PARM_T KEY_CD="mandatoryRoute"
        RTE_NODE_CFG_PARM_ID="2177" RTE_NODE_ID="2063" VAL="false"/>
    <KREW_RTE_NODE_CFG_PARM_T KEY_CD="finalApproval"
        RTE_NODE_CFG_PARM_ID="2178" RTE_NODE_ID="2063" VAL="false"/>
    <KREW_RTE_NODE_CFG_PARM_T KEY_CD="ruleSelector"
        RTE_NODE_CFG_PARM_ID="2179" RTE_NODE_ID="2063" VAL="Template"/>
    <KREW_RTE_NODE_CFG_PARM_T KEY_CD="contentFragment"
        RTE_NODE_CFG_PARM_ID="2180" RTE_NODE_ID="2065" VAL="&lt;start name=&quot;Initiated&quot;>&lt;activationType>P&lt;/activationType>&lt;mandatoryRoute>false&lt;/mandatoryRoute>&lt;finalApproval>false&lt;/finalApproval>&lt;/start>"/>
    <KREW_RTE_NODE_CFG_PARM_T KEY_CD="activationType"
        RTE_NODE_CFG_PARM_ID="2181" RTE_NODE_ID="2065" VAL="P"/>
    <KREW_RTE_NODE_CFG_PARM_T KEY_CD="mandatoryRoute"
        RTE_NODE_CFG_PARM_ID="2182" RTE_NODE_ID="2065" VAL="false"/>
    <KREW_RTE_NODE_CFG_PARM_T KEY_CD="finalApproval"
        RTE_NODE_CFG_PARM_ID="2183" RTE_NODE_ID="2065" VAL="false"/>
    <KREW_RTE_NODE_CFG_PARM_T KEY_CD="ruleSelector"
        RTE_NODE_CFG_PARM_ID="2184" RTE_NODE_ID="2065" VAL="Template"/>
    <KREW_RTE_NODE_CFG_PARM_T KEY_CD="contentFragment"
        RTE_NODE_CFG_PARM_ID="2185" RTE_NODE_ID="2067" VAL="&lt;start name=&quot;Initiated&quot;>&lt;activationType>P&lt;/activationType>&lt;mandatoryRoute>false&lt;/mandatoryRoute>&lt;finalApproval>false&lt;/finalApproval>&lt;/start>"/>
    <KREW_RTE_NODE_CFG_PARM_T KEY_CD="activationType"
        RTE_NODE_CFG_PARM_ID="2186" RTE_NODE_ID="2067" VAL="P"/>
    <KREW_RTE_NODE_CFG_PARM_T KEY_CD="mandatoryRoute"
        RTE_NODE_CFG_PARM_ID="2187" RTE_NODE_ID="2067" VAL="false"/>
    <KREW_RTE_NODE_CFG_PARM_T KEY_CD="finalApproval"
        RTE_NODE_CFG_PARM_ID="2188" RTE_NODE_ID="2067" VAL="false"/>
    <KREW_RTE_NODE_CFG_PARM_T KEY_CD="ruleSelector"
        RTE_NODE_CFG_PARM_ID="2189" RTE_NODE_ID="2067" VAL="Template"/>
    <KREW_RTE_NODE_CFG_PARM_T KEY_CD="contentFragment"
        RTE_NODE_CFG_PARM_ID="2380" RTE_NODE_ID="2840" VAL="&lt;start name=&quot;PreRoute&quot;>&lt;activationType>S&lt;/activationType>&lt;mandatoryRoute>false&lt;/mandatoryRoute>&lt;finalApproval>false&lt;/finalApproval>&lt;/start>"/>
    <KREW_RTE_NODE_CFG_PARM_T KEY_CD="activationType"
        RTE_NODE_CFG_PARM_ID="2381" RTE_NODE_ID="2840" VAL="S"/>
    <KREW_RTE_NODE_CFG_PARM_T KEY_CD="mandatoryRoute"
        RTE_NODE_CFG_PARM_ID="2382" RTE_NODE_ID="2840" VAL="false"/>
    <KREW_RTE_NODE_CFG_PARM_T KEY_CD="finalApproval"
        RTE_NODE_CFG_PARM_ID="2383" RTE_NODE_ID="2840" VAL="false"/>
    <KREW_RTE_NODE_CFG_PARM_T KEY_CD="ruleSelector"
        RTE_NODE_CFG_PARM_ID="2384" RTE_NODE_ID="2840" VAL="Template"/>
    <KREW_RTE_NODE_CFG_PARM_T KEY_CD="contentFragment"
        RTE_NODE_CFG_PARM_ID="2430" RTE_NODE_ID="2898" VAL="&lt;start name=&quot;AdHoc&quot;/>"/>
    <KREW_RTE_NODE_CFG_PARM_T KEY_CD="ruleSelector"
        RTE_NODE_CFG_PARM_ID="2431" RTE_NODE_ID="2898" VAL="Template"/>
    <KREW_RTE_NODE_CFG_PARM_T KEY_CD="contentFragment"
        RTE_NODE_CFG_PARM_ID="2432" RTE_NODE_ID="2899" VAL="&lt;role name=&quot;RoleType&quot;>&lt;qualifierResolverClass>org.kuali.rice.kim.impl.type.KimTypeQualifierResolver&lt;/qualifierResolverClass>&lt;activationType>P&lt;/activationType>&lt;/role>"/>
    <KREW_RTE_NODE_CFG_PARM_T KEY_CD="qualifierResolverClass"
        RTE_NODE_CFG_PARM_ID="2433" RTE_NODE_ID="2899" VAL="org.kuali.rice.kim.impl.type.KimTypeQualifierResolver"/>
    <KREW_RTE_NODE_CFG_PARM_T KEY_CD="activationType"
        RTE_NODE_CFG_PARM_ID="2434" RTE_NODE_ID="2899" VAL="P"/>
    <KREW_RTE_NODE_CFG_PARM_T KEY_CD="ruleSelector"
        RTE_NODE_CFG_PARM_ID="2435" RTE_NODE_ID="2899" VAL="Template"/>
    <KREW_RTE_NODE_CFG_PARM_T KEY_CD="contentFragment"
        RTE_NODE_CFG_PARM_ID="2436" RTE_NODE_ID="2901" VAL="&lt;start name=&quot;AdHoc&quot;/>"/>
    <KREW_RTE_NODE_CFG_PARM_T KEY_CD="ruleSelector"
        RTE_NODE_CFG_PARM_ID="2437" RTE_NODE_ID="2901" VAL="Template"/>
    <KREW_RTE_NODE_CFG_PARM_T KEY_CD="contentFragment"
        RTE_NODE_CFG_PARM_ID="2438" RTE_NODE_ID="2902" VAL="&lt;role name=&quot;GroupType&quot;>&lt;qualifierResolverClass>org.kuali.rice.kim.impl.type.KimTypeQualifierResolver&lt;/qualifierResolverClass>&lt;activationType>P&lt;/activationType>&lt;/role>"/>
    <KREW_RTE_NODE_CFG_PARM_T KEY_CD="qualifierResolverClass"
        RTE_NODE_CFG_PARM_ID="2439" RTE_NODE_ID="2902" VAL="org.kuali.rice.kim.impl.type.KimTypeQualifierResolver"/>
    <KREW_RTE_NODE_CFG_PARM_T KEY_CD="activationType"
        RTE_NODE_CFG_PARM_ID="2440" RTE_NODE_ID="2902" VAL="P"/>
    <KREW_RTE_NODE_CFG_PARM_T KEY_CD="ruleSelector"
        RTE_NODE_CFG_PARM_ID="2441" RTE_NODE_ID="2902" VAL="Template"/>
    <KREW_RTE_NODE_CFG_PARM_T KEY_CD="contentFragment"
        RTE_NODE_CFG_PARM_ID="2442" RTE_NODE_ID="2904" VAL="&lt;start name=&quot;AdHoc&quot;/>"/>
    <KREW_RTE_NODE_CFG_PARM_T KEY_CD="ruleSelector"
        RTE_NODE_CFG_PARM_ID="2443" RTE_NODE_ID="2904" VAL="Template"/>
    <KREW_RTE_NODE_CFG_PARM_T KEY_CD="contentFragment"
        RTE_NODE_CFG_PARM_ID="2444" RTE_NODE_ID="2905" VAL="&lt;role name=&quot;GroupType&quot;>&lt;qualifierResolverClass>org.kuali.rice.kim.impl.type.KimTypeQualifierResolver&lt;/qualifierResolverClass>&lt;activationType>P&lt;/activationType>&lt;/role>"/>
    <KREW_RTE_NODE_CFG_PARM_T KEY_CD="qualifierResolverClass"
        RTE_NODE_CFG_PARM_ID="2445" RTE_NODE_ID="2905" VAL="org.kuali.rice.kim.impl.type.KimTypeQualifierResolver"/>
    <KREW_RTE_NODE_CFG_PARM_T KEY_CD="activationType"
        RTE_NODE_CFG_PARM_ID="2446" RTE_NODE_ID="2905" VAL="P"/>
    <KREW_RTE_NODE_CFG_PARM_T KEY_CD="ruleSelector"
        RTE_NODE_CFG_PARM_ID="2447" RTE_NODE_ID="2905" VAL="Template"/>
    <KREW_RTE_NODE_CFG_PARM_T KEY_CD="contentFragment"
        RTE_NODE_CFG_PARM_ID="2448" RTE_NODE_ID="2906" VAL="&lt;role name=&quot;RoleType&quot;>&lt;qualifierResolverClass>org.kuali.rice.kim.impl.type.KimTypeQualifierResolver&lt;/qualifierResolverClass>&lt;activationType>P&lt;/activationType>&lt;/role>"/>
    <KREW_RTE_NODE_CFG_PARM_T KEY_CD="qualifierResolverClass"
        RTE_NODE_CFG_PARM_ID="2449" RTE_NODE_ID="2906" VAL="org.kuali.rice.kim.impl.type.KimTypeQualifierResolver"/>
    <KREW_RTE_NODE_CFG_PARM_T KEY_CD="activationType"
        RTE_NODE_CFG_PARM_ID="2450" RTE_NODE_ID="2906" VAL="P"/>
    <KREW_RTE_NODE_CFG_PARM_T KEY_CD="ruleSelector"
        RTE_NODE_CFG_PARM_ID="2451" RTE_NODE_ID="2906" VAL="Template"/>
    <KREW_RTE_NODE_CFG_PARM_T KEY_CD="contentFragment"
        RTE_NODE_CFG_PARM_ID="2452" RTE_NODE_ID="2908" VAL="&lt;start name=&quot;AdHoc&quot;/>"/>
    <KREW_RTE_NODE_CFG_PARM_T KEY_CD="ruleSelector"
        RTE_NODE_CFG_PARM_ID="2453" RTE_NODE_ID="2908" VAL="Template"/>
    <KREW_RTE_NODE_CFG_PARM_T KEY_CD="contentFragment"
        RTE_NODE_CFG_PARM_ID="2454" RTE_NODE_ID="2910" VAL="&lt;start name=&quot;AdHoc&quot;/>"/>
    <KREW_RTE_NODE_CFG_PARM_T KEY_CD="ruleSelector"
        RTE_NODE_CFG_PARM_ID="2455" RTE_NODE_ID="2910" VAL="Template"/>
    <KREW_RTE_NODE_CFG_PARM_T KEY_CD="contentFragment"
        RTE_NODE_CFG_PARM_ID="2470" RTE_NODE_ID="2917" VAL="&lt;start name=&quot;Initiated&quot;>&#xa;&lt;activationType>P&lt;/activationType>&#xa;&lt;mandatoryRoute>false&lt;/mandatoryRoute>&#xa;&lt;finalApproval>false&lt;/finalApproval>&#xa;&lt;/start>&#xa;"/>
    <KREW_RTE_NODE_CFG_PARM_T KEY_CD="activationType"
        RTE_NODE_CFG_PARM_ID="2471" RTE_NODE_ID="2917" VAL="P"/>
    <KREW_RTE_NODE_CFG_PARM_T KEY_CD="mandatoryRoute"
        RTE_NODE_CFG_PARM_ID="2472" RTE_NODE_ID="2917" VAL="false"/>
    <KREW_RTE_NODE_CFG_PARM_T KEY_CD="finalApproval"
        RTE_NODE_CFG_PARM_ID="2473" RTE_NODE_ID="2917" VAL="false"/>
    <KREW_RTE_NODE_CFG_PARM_T KEY_CD="ruleSelector"
        RTE_NODE_CFG_PARM_ID="2474" RTE_NODE_ID="2917" VAL="Template"/>
    <KREW_RTE_NODE_CFG_PARM_T KEY_CD="contentFragment"
        RTE_NODE_CFG_PARM_ID="2475" RTE_NODE_ID="2919" VAL="&lt;start name=&quot;Initiated&quot;>&#xa;&lt;activationType>P&lt;/activationType>&#xa;&lt;mandatoryRoute>false&lt;/mandatoryRoute>&#xa;&lt;finalApproval>false&lt;/finalApproval>&#xa;&lt;/start>&#xa;"/>
    <KREW_RTE_NODE_CFG_PARM_T KEY_CD="activationType"
        RTE_NODE_CFG_PARM_ID="2476" RTE_NODE_ID="2919" VAL="P"/>
    <KREW_RTE_NODE_CFG_PARM_T KEY_CD="mandatoryRoute"
        RTE_NODE_CFG_PARM_ID="2477" RTE_NODE_ID="2919" VAL="false"/>
    <KREW_RTE_NODE_CFG_PARM_T KEY_CD="finalApproval"
        RTE_NODE_CFG_PARM_ID="2478" RTE_NODE_ID="2919" VAL="false"/>
    <KREW_RTE_NODE_CFG_PARM_T KEY_CD="ruleSelector"
        RTE_NODE_CFG_PARM_ID="2479" RTE_NODE_ID="2919" VAL="Template"/>
    <KREW_RTE_NODE_CFG_PARM_T KEY_CD="contentFragment"
        RTE_NODE_CFG_PARM_ID="2480" RTE_NODE_ID="2921" VAL="&lt;start name=&quot;Initiated&quot;>&#xa;&lt;activationType>P&lt;/activationType>&#xa;&lt;mandatoryRoute>false&lt;/mandatoryRoute>&#xa;&lt;finalApproval>false&lt;/finalApproval>&#xa;&lt;/start>&#xa;"/>
    <KREW_RTE_NODE_CFG_PARM_T KEY_CD="activationType"
        RTE_NODE_CFG_PARM_ID="2481" RTE_NODE_ID="2921" VAL="P"/>
    <KREW_RTE_NODE_CFG_PARM_T KEY_CD="mandatoryRoute"
        RTE_NODE_CFG_PARM_ID="2482" RTE_NODE_ID="2921" VAL="false"/>
    <KREW_RTE_NODE_CFG_PARM_T KEY_CD="finalApproval"
        RTE_NODE_CFG_PARM_ID="2483" RTE_NODE_ID="2921" VAL="false"/>
    <KREW_RTE_NODE_CFG_PARM_T KEY_CD="ruleSelector"
        RTE_NODE_CFG_PARM_ID="2484" RTE_NODE_ID="2921" VAL="Template"/>
</dataset>
