<?xml version="1.0" encoding="UTF-8"?>
<!--  Auto-generated by the Maven Impex Plugin -->
<!DOCTYPE dataset SYSTEM "data.dtd">
<dataset>
    <PUR_PO_CST_SRC_T PO_CST_SRC_CD="CON" OBJ_ID="636024D36C5F8EC6E0404F8189D80405" VER_NBR="1.0" PO_CST_SRC_DESC="PRICING AGREEMENT FIRM" DOBJ_MAINT_CD_ACTV_IND="Y" ITM_UNIT_PRC_UPR_VAR_PCT="0.0" ITM_UNIT_PRC_LWR_VAR_PCT="0.0" />
    <PUR_PO_CST_SRC_T PO_CST_SRC_CD="COOP" OBJ_ID="636024D36C608EC6E0404F8189D80405" VER_NBR="1.0" PO_CST_SRC_DESC="COOPERATIVE AGREEMENT" DOBJ_MAINT_CD_ACTV_IND="Y" ITM_UNIT_PRC_UPR_VAR_PCT="0.0" ITM_UNIT_PRC_LWR_VAR_PCT="0.0" />
    <PUR_PO_CST_SRC_T PO_CST_SRC_CD="EST" OBJ_ID="636024D36C628EC6E0404F8189D80405" VER_NBR="1.0" PO_CST_SRC_DESC="ESTIMATE" DOBJ_MAINT_CD_ACTV_IND="Y" ITM_UNIT_PRC_UPR_VAR_PCT="10.0" ITM_UNIT_PRC_LWR_VAR_PCT="50.0" />
    <PUR_PO_CST_SRC_T PO_CST_SRC_CD="GSA" OBJ_ID="636024D36C638EC6E0404F8189D80405" VER_NBR="1.0" PO_CST_SRC_DESC="GSA" DOBJ_MAINT_CD_ACTV_IND="Y" />
    <PUR_PO_CST_SRC_T PO_CST_SRC_CD="QUOT" OBJ_ID="636024D36C6A8EC6E0404F8189D80405" VER_NBR="1.0" PO_CST_SRC_DESC="QUOTE" DOBJ_MAINT_CD_ACTV_IND="Y" />
    <PUR_PO_CST_SRC_T PO_CST_SRC_CD="UTIL" OBJ_ID="636024D36C6E8EC6E0404F8189D80405" VER_NBR="1.0" PO_CST_SRC_DESC="UTILITY" DOBJ_MAINT_CD_ACTV_IND="Y" ITM_UNIT_PRC_UPR_VAR_PCT="50.0" ITM_UNIT_PRC_LWR_VAR_PCT="50.0" />
    <PUR_PO_CST_SRC_T PO_CST_SRC_CD="VAR" OBJ_ID="636024D36C6F8EC6E0404F8189D80405" VER_NBR="1.0" PO_CST_SRC_DESC="PRICING AGREEMENT VARIABLE" DOBJ_MAINT_CD_ACTV_IND="Y" ITM_UNIT_PRC_UPR_VAR_PCT="20.0" ITM_UNIT_PRC_LWR_VAR_PCT="50.0" />
    <PUR_PO_CST_SRC_T PO_CST_SRC_CD="VEN" OBJ_ID="636024D36C708EC6E0404F8189D80405" VER_NBR="1.0" PO_CST_SRC_DESC="VENDOR PRICE" DOBJ_MAINT_CD_ACTV_IND="Y" />
</dataset>
